<annotation>
	<folder>img</folder>
	<filename>291.jpg</filename>
	<path>/home/mustang/img/291.jpg</path>
	<source>
		<database>Unknown</database>
	</source>
	<size>
		<width>800</width>
		<height>600</height>
		<depth>3</depth>
	</size>
	<segmented>0</segmented>
	<object>
		<name>label0</name>
		<pose>Unspecified</pose>
		<truncated>0</truncated>
		<difficult>0</difficult>
		<bndbox>
			<xmin>514</xmin>
			<ymin>142</ymin>
			<xmax>608</xmax>
			<ymax>554</ymax>
		</bndbox>
	</object>
	<object>
		<name>label2</name>
		<pose>Unspecified</pose>
		<truncated>1</truncated>
		<difficult>0</difficult>
		<bndbox>
			<xmin>15</xmin>
			<ymin>11</ymin>
			<xmax>215</xmax>
			<ymax>600</ymax>
		</bndbox>
	</object>
</annotation>
